[
	{
		"date": "May 7-8 / Beijing",
		"title": "GMIC (Global Mobile Internet Conference)",
		"visit": "Visit GMIC",
		"link": "http://beijing.thegmic.com/",
		"image": "/image/event/logo04.jpg",
		"beginAt": 1364572800,
		"endAt": 1368028800
	},
	{
		"date": "May 14-15 / San Francisco",
		"title": "MobileGamingUSAWest (Global Mobile Internet Conference)<br><font size='-1'>Appier CEO Chih-Han is invited as a panelist in 'Exploring the evolution of the mobile gaming marketplace in Asia' forum</font>",
		"visit": "Visit MobileGamingUSAWest",
		"link": "http://videogamesintelligence.com/mobile-gaming-west/",
		"image": "/image/event/logo05.jpg",
		"beginAt": 1368518400,
		"endAt": 1368637200
	}
]
